hdc_installer/__init__.py
hdc_installer/__main__.py
hdc_installer/cli.py
hdc_installer-0.1.0.dist-info/licenses/LICENSE
hdc_installer-0.1.0.dist-info/METADATA
hdc_installer-0.1.0.dist-info/WHEEL
hdc_installer-0.1.0.dist-info/entry_points.txt
hdc_installer-0.1.0.dist-info/top_level.txt
hdc_installer-0.1.0.dist-info/RECORD
