Metadata-Version: 2.4
Name: hdc_installer
Version: 0.1.0
Summary: A lightweight installer for HarmonyOS HDC tools
Home-page: https://github.com/youngfreeFJS/harmony_hdc_bin_collection
Author: youngfreefjs
Author-email: youngfreefjs@gmail.com
Classifier: Programming Language :: Python :: 3
Classifier: License :: OSI Approved :: MIT License
Classifier: Operating System :: OS Independent
Requires-Python: >=3.6
License-File: LICENSE
Requires-Dist: click>=8.0.0
Dynamic: author
Dynamic: author-email
Dynamic: classifier
Dynamic: description
Dynamic: description-content-type
Dynamic: home-page
Dynamic: license-file
Dynamic: requires-dist
Dynamic: requires-python
Dynamic: summary
